setup.py
cloudfront/__init__.py
django_cloudfront.egg-info/PKG-INFO
django_cloudfront.egg-info/SOURCES.txt
django_cloudfront.egg-info/dependency_links.txt
django_cloudfront.egg-info/not-zip-safe
django_cloudfront.egg-info/requires.txt
django_cloudfront.egg-info/top_level.txt