Metadata-Version: 1.1
Name: django-cloudfront
Version: 0.1
Summary: cloudfront private content signing for django
Home-page: http://github.com/tzangms/django_cloudfront
Author: tzangms
Author-email: tzangms@gmail.com
License: MIT
Keywords: django cloudfront
Platform: UNKNOWN
Classifier: Programming Language :: Python
Classifier: Topic :: Software Development :: Libraries :: Python Modules
Classifier: Framework :: Django
Classifier: Environment :: Web Environment
